appcms
