Metadata-Version: 1.0
Name: django-appcms
Version: 0.0.3
Summary: Templatetags for inserting django-cms placeholders in app templates.
Home-page: http://github.com/codemill/django-appcms
Author: Ludvig Widman, CodeMill AB
Author-email: opensource@codemill.se
License: UNKNOWN
Platform: UNKNOWN
